[
  {
    "c": 127.61,
    "d": 0.07,
    "dp": 0.0549,
    "h": 127.82,
    "l": 127.11,
    "o": 127.64,
    "pc": 127.54,
    "t": 1761141628,
    "symbol": "ABT",
    "date": "2025-10-22"
  },
  {
    "c": 230.18,
    "d": -1.21,
    "dp": -0.5229,
    "h": 232.16,
    "l": 230,
    "o": 231.35,
    "pc": 231.39,
    "t": 1761141631,
    "symbol": "ABBV",
    "date": "2025-10-22"
  },
  {
    "c": 248.16,
    "d": -2.35,
    "dp": -0.9381,
    "h": 251.35,
    "l": 247.17,
    "o": 251.35,
    "pc": 250.51,
    "t": 1761141629,
    "symbol": "ACN",
    "date": "2025-10-22"
  },
  {
    "c": 254.24,
    "d": 3.78,
    "dp": 1.5092,
    "h": 256.16,
    "l": 253.11,
    "o": 254.08,
    "pc": 250.46,
    "t": 1761141631,
    "symbol": "GOOGL",
    "date": "2025-10-22"
  },
  {
    "c": 218.67,
    "d": -3.36,
    "dp": -1.5133,
    "h": 220.83,
    "l": 218.06,
    "o": 220.83,
    "pc": 222.03,
    "t": 1761141630,
    "symbol": "AMZN",
    "date": "2025-10-22"
  },
  {
    "c": 2.16,
    "d": 0.03,
    "dp": 1.4085,
    "h": 2.16,
    "l": 2.08,
    "o": 2.13,
    "pc": 2.13,
    "t": 1761141227,
    "symbol": "AMBR",
    "date": "2025-10-22"
  },
  {
    "c": 260.4,
    "d": -2.37,
    "dp": -0.9019,
    "h": 262.85,
    "l": 259.93,
    "o": 262.34,
    "pc": 262.77,
    "t": 1761141629,
    "symbol": "AAPL",
    "date": "2025-10-22"
  },
  {
    "c": 566.55,
    "d": 13.91,
    "dp": 2.517,
    "h": 570,
    "l": 551,
    "o": 551,
    "pc": 552.64,
    "t": 1761141629,
    "symbol": "APP",
    "date": "2025-10-22"
  },
  {
    "c": 83.7,
    "d": 0.48,
    "dp": 0.5768,
    "h": 83.75,
    "l": 83.06,
    "o": 83.06,
    "pc": 83.22,
    "t": 1761141631,
    "symbol": "AZN",
    "date": "2025-10-22"
  },
  {
    "c": 51.14,
    "d": -0.38,
    "dp": -0.7376,
    "h": 51.59,
    "l": 51.02,
    "o": 51.59,
    "pc": 51.52,
    "t": 1761141631,
    "symbol": "BAC",
    "date": "2025-10-22"
  },
  {
    "c": 491.21,
    "d": -0.08,
    "dp": -0.0163,
    "h": 492.98,
    "l": 490.74,
    "o": 491.66,
    "pc": 491.29,
    "t": 1761141625,
    "symbol": "BRK.B",
    "date": "2025-10-22"
  },
  {
    "c": 345.6,
    "d": 2.94,
    "dp": 0.858,
    "h": 348.01,
    "l": 343.09,
    "o": 346.25,
    "pc": 342.66,
    "t": 1761141631,
    "symbol": "AVGO",
    "date": "2025-10-22"
  },
  {
    "c": 154.92,
    "d": 1.13,
    "dp": 0.7348,
    "h": 155.14,
    "l": 154.39,
    "o": 154.57,
    "pc": 153.79,
    "t": 1761141631,
    "symbol": "CVX",
    "date": "2025-10-22"
  },
  {
    "c": 129.7,
    "d": -0.15,
    "dp": -0.1155,
    "h": 131,
    "l": 128.09,
    "o": 129,
    "pc": 129.85,
    "t": 1761141630,
    "symbol": "CRCL",
    "date": "2025-10-22"
  },
  {
    "c": 70.31,
    "d": -0.41,
    "dp": -0.5798,
    "h": 70.97,
    "l": 70.145,
    "o": 70.81,
    "pc": 70.72,
    "t": 1761141630,
    "symbol": "CSCO",
    "date": "2025-10-22"
  },
  {
    "c": 70.685,
    "d": -0.535,
    "dp": -0.7512,
    "h": 71.5,
    "l": 70.6,
    "o": 70.88,
    "pc": 71.22,
    "t": 1761141630,
    "symbol": "KO",
    "date": "2025-10-22"
  },
  {
    "c": 327.72,
    "d": -10.9,
    "dp": -3.2189,
    "h": 334.72,
    "l": 325.0187,
    "o": 333.26,
    "pc": 338.62,
    "t": 1761141629,
    "symbol": "COIN",
    "date": "2025-10-22"
  },
  {
    "c": 29.595,
    "d": -0.375,
    "dp": -1.2513,
    "h": 30.05,
    "l": 29.47,
    "o": 30.05,
    "pc": 29.97,
    "t": 1761141630,
    "symbol": "CMCSA",
    "date": "2025-10-22"
  },
  {
    "c": 503.53,
    "d": -0.42,
    "dp": -0.0833,
    "h": 504.38,
    "l": 498.01,
    "o": 503.51,
    "pc": 503.95,
    "t": 1761141619,
    "symbol": "CRWD",
    "date": "2025-10-22"
  },
  {
    "c": 216.66,
    "d": -4.11,
    "dp": -1.8617,
    "h": 222.97,
    "l": 215.28,
    "o": 221.19,
    "pc": 220.77,
    "t": 1761141628,
    "symbol": "DHR",
    "date": "2025-10-22"
  },
  {
    "c": 14.02,
    "d": -0.43,
    "dp": -2.9758,
    "h": 14.45,
    "l": 13.895,
    "o": 14.45,
    "pc": 14.45,
    "t": 1761141630,
    "symbol": "DFDV",
    "date": "2025-10-22"
  },
  {
    "c": 804.66,
    "d": 5.09,
    "dp": 0.6366,
    "h": 804.9,
    "l": 793.82,
    "o": 799.36,
    "pc": 799.57,
    "t": 1761141628,
    "symbol": "LLY",
    "date": "2025-10-22"
  },
  {
    "c": 113.75,
    "d": 1.04,
    "dp": 0.9227,
    "h": 113.77,
    "l": 113.05,
    "o": 113.05,
    "pc": 112.71,
    "t": 1761141629,
    "symbol": "XOM",
    "date": "2025-10-22"
  },
  {
    "c": 23.07,
    "d": 0.27,
    "dp": 1.1842,
    "h": 23.0899,
    "l": 22.67,
    "o": 22.76,
    "pc": 22.8,
    "t": 1761141631,
    "symbol": "GME",
    "date": "2025-10-22"
  },
  {
    "c": 375.09,
    "d": -2.15,
    "dp": -0.5699,
    "h": 380.32,
    "l": 372.31,
    "o": 380.32,
    "pc": 377.24,
    "t": 1761141631,
    "symbol": "GLD",
    "date": "2025-10-22"
  },
  {
    "c": 755.225,
    "d": -3.755,
    "dp": -0.4947,
    "h": 760.61,
    "l": 754.32,
    "o": 760.07,
    "pc": 758.98,
    "t": 1761141623,
    "symbol": "GS",
    "date": "2025-10-22"
  },
  {
    "c": 389.435,
    "d": -1.465,
    "dp": -0.3748,
    "h": 392.1,
    "l": 389.24,
    "o": 392.1,
    "pc": 390.9,
    "t": 1761141629,
    "symbol": "HD",
    "date": "2025-10-22"
  },
  {
    "c": 208.21,
    "d": -0.87,
    "dp": -0.4161,
    "h": 210.185,
    "l": 207.86,
    "o": 209.69,
    "pc": 209.08,
    "t": 1761141629,
    "symbol": "HON",
    "date": "2025-10-22"
  },
  {
    "c": 37.7133,
    "d": -0.4067,
    "dp": -1.0669,
    "h": 37.97,
    "l": 37.08,
    "o": 37.97,
    "pc": 38.12,
    "t": 1761141630,
    "symbol": "INTC",
    "date": "2025-10-22"
  },
  {
    "c": 284.94,
    "d": 2.89,
    "dp": 1.0246,
    "h": 286.25,
    "l": 281.35,
    "o": 282.38,
    "pc": 282.05,
    "t": 1761141631,
    "symbol": "IBM",
    "date": "2025-10-22"
  },
  {
    "c": 192.33,
    "d": 0.45,
    "dp": 0.2345,
    "h": 192.785,
    "l": 191.775,
    "o": 192.04,
    "pc": 191.88,
    "t": 1761141629,
    "symbol": "JNJ",
    "date": "2025-10-22"
  },
  {
    "c": 296.3,
    "d": -0.79,
    "dp": -0.2659,
    "h": 298.0599,
    "l": 295.73,
    "o": 298,
    "pc": 297.09,
    "t": 1761141619,
    "symbol": "JPM",
    "date": "2025-10-22"
  },
  {
    "c": 448.955,
    "d": -1.125,
    "dp": -0.25,
    "h": 450.355,
    "l": 447.75,
    "o": 449.63,
    "pc": 450.08,
    "t": 1761141629,
    "symbol": "LIN",
    "date": "2025-10-22"
  },
  {
    "c": 83.15,
    "d": -1.11,
    "dp": -1.3174,
    "h": 83.5727,
    "l": 80.5,
    "o": 82.58,
    "pc": 84.26,
    "t": 1761141630,
    "symbol": "MRVL",
    "date": "2025-10-22"
  },
  {
    "c": 570.39,
    "d": -1.64,
    "dp": -0.2867,
    "h": 574.99,
    "l": 568.58,
    "o": 574.99,
    "pc": 572.03,
    "t": 1761141602,
    "symbol": "MA",
    "date": "2025-10-22"
  },
  {
    "c": 307.845,
    "d": 0.365,
    "dp": 0.1187,
    "h": 308.5,
    "l": 307.2,
    "o": 307.34,
    "pc": 307.48,
    "t": 1761141620,
    "symbol": "MCD",
    "date": "2025-10-22"
  },
  {
    "c": 96.09,
    "d": 0.26,
    "dp": 0.2713,
    "h": 97.24,
    "l": 95.55,
    "o": 96.32,
    "pc": 95.83,
    "t": 1761141631,
    "symbol": "MDT",
    "date": "2025-10-22"
  },
  {
    "c": 87.33,
    "d": -0.29,
    "dp": -0.331,
    "h": 87.97,
    "l": 87.0139,
    "o": 87.27,
    "pc": 87.62,
    "t": 1761141631,
    "symbol": "MRK",
    "date": "2025-10-22"
  },
  {
    "c": 736.95,
    "d": 3.68,
    "dp": 0.5019,
    "h": 738.98,
    "l": 731.059,
    "o": 734.58,
    "pc": 733.27,
    "t": 1761141628,
    "symbol": "META",
    "date": "2025-10-22"
  },
  {
    "c": 522.505,
    "d": 4.845,
    "dp": 0.9359,
    "h": 523.54,
    "l": 517.08,
    "o": 517.08,
    "pc": 517.66,
    "t": 1761141631,
    "symbol": "MSFT",
    "date": "2025-10-22"
  },
  {
    "c": 296.87,
    "d": -5.04,
    "dp": -1.6694,
    "h": 297.96,
    "l": 292.2,
    "o": 295.42,
    "pc": 301.91,
    "t": 1761141629,
    "symbol": "MSTR",
    "date": "2025-10-22"
  },
  {
    "c": 610.92,
    "d": -0.46,
    "dp": -0.0752,
    "h": 611.68,
    "l": 608.6301,
    "o": 611.68,
    "pc": 611.38,
    "t": 1761141683,
    "symbol": "QQQ",
    "date": "2025-10-22"
  },
  {
    "c": 1133.78,
    "d": -107.57,
    "dp": -8.6656,
    "h": 1163,
    "l": 1128.7,
    "o": 1163,
    "pc": 1241.35,
    "t": 1761141683,
    "symbol": "NFLX",
    "date": "2025-10-22"
  },
  {
    "c": 53.67,
    "d": -1.11,
    "dp": -2.0263,
    "h": 53.77,
    "l": 53.4534,
    "o": 53.77,
    "pc": 54.78,
    "t": 1761141682,
    "symbol": "NVO",
    "date": "2025-10-22"
  },
  {
    "c": 182.9518,
    "d": 1.7918,
    "dp": 0.9891,
    "h": 183.44,
    "l": 180.29,
    "o": 181.33,
    "pc": 181.16,
    "t": 1761141683,
    "symbol": "NVDA",
    "date": "2025-10-22"
  },
  {
    "c": 275.615,
    "d": 0.465,
    "dp": 0.169,
    "h": 277.2,
    "l": 273,
    "o": 275.16,
    "pc": 275.15,
    "t": 1761141683,
    "symbol": "ORCL",
    "date": "2025-10-22"
  },
  {
    "c": 181.0603,
    "d": -0.4497,
    "dp": -0.2478,
    "h": 182.21,
    "l": 179.25,
    "o": 180.93,
    "pc": 181.51,
    "t": 1761141683,
    "symbol": "PLTR",
    "date": "2025-10-22"
  },
  {
    "c": 152.945,
    "d": -0.235,
    "dp": -0.1534,
    "h": 153.82,
    "l": 152.71,
    "o": 152.96,
    "pc": 153.18,
    "t": 1761141682,
    "symbol": "PEP",
    "date": "2025-10-22"
  },
  {
    "c": 24.795,
    "d": -0.055,
    "dp": -0.2213,
    "h": 24.8459,
    "l": 24.7,
    "o": 24.82,
    "pc": 24.85,
    "t": 1761141683,
    "symbol": "PFE",
    "date": "2025-10-22"
  },
  {
    "c": 153.005,
    "d": 1.005,
    "dp": 0.6612,
    "h": 153.86,
    "l": 151,
    "o": 151.92,
    "pc": 152,
    "t": 1761141678,
    "symbol": "PM",
    "date": "2025-10-22"
  },
  {
    "c": 150.965,
    "d": -0.655,
    "dp": -0.432,
    "h": 151.78,
    "l": 150.785,
    "o": 151.78,
    "pc": 151.62,
    "t": 1761141679,
    "symbol": "PG",
    "date": "2025-10-22"
  },
  {
    "c": 129.21,
    "d": -2.63,
    "dp": -1.9948,
    "h": 132.36,
    "l": 127.77,
    "o": 130.9,
    "pc": 131.84,
    "t": 1761141681,
    "symbol": "HOOD",
    "date": "2025-10-22"
  },
  {
    "c": 258.8,
    "d": -4.61,
    "dp": -1.7501,
    "h": 263.65,
    "l": 257.83,
    "o": 263.65,
    "pc": 263.41,
    "t": 1761141679,
    "symbol": "CRM",
    "date": "2025-10-22"
  },
  {
    "c": 671.27,
    "d": -0.02,
    "dp": -0.003,
    "h": 672.26,
    "l": 670.45,
    "o": 672.26,
    "pc": 671.29,
    "t": 1761141683,
    "symbol": "SPY",
    "date": "2025-10-22"
  },
  {
    "c": 441.33,
    "d": -1.27,
    "dp": -0.2869,
    "h": 445.539,
    "l": 439.6,
    "o": 443.56,
    "pc": 442.6,
    "t": 1761141683,
    "symbol": "TSLA",
    "date": "2025-10-22"
  },
  {
    "c": 560.11,
    "d": 2.12,
    "dp": 0.3799,
    "h": 571.29,
    "l": 550.88,
    "o": 559.55,
    "pc": 557.99,
    "t": 1761141678,
    "symbol": "TMO",
    "date": "2025-10-22"
  },
  {
    "c": 107.48,
    "d": -0.29,
    "dp": -0.2691,
    "h": 107.87,
    "l": 106.28,
    "o": 107.87,
    "pc": 107.77,
    "t": 1761141683,
    "symbol": "TQQQ",
    "date": "2025-10-22"
  },
  {
    "c": 360.93,
    "d": -4.44,
    "dp": -1.2152,
    "h": 365.55,
    "l": 358,
    "o": 365.55,
    "pc": 365.37,
    "t": 1761141681,
    "symbol": "UNH",
    "date": "2025-10-22"
  },
  {
    "c": 330.84,
    "d": -0.07,
    "dp": -0.0212,
    "h": 331.2259,
    "l": 330.51,
    "o": 331.06,
    "pc": 330.91,
    "t": 1761141681,
    "symbol": "VTI",
    "date": "2025-10-22"
  },
  {
    "c": 346.53,
    "d": -0.68,
    "dp": -0.1958,
    "h": 347.82,
    "l": 344.5,
    "o": 347.07,
    "pc": 347.21,
    "t": 1761141663,
    "symbol": "V",
    "date": "2025-10-22"
  },
  {
    "c": 105.745,
    "d": -0.475,
    "dp": -0.4472,
    "h": 106.65,
    "l": 105.655,
    "o": 106.34,
    "pc": 106.22,
    "t": 1761141717,
    "symbol": "WMT",
    "date": "2025-10-22"
  }
]